ciphercaesar/__init__.py
ciphercaesar/cipher_funcs.py
ciphercaesar-0.1.1.dist-info/LICENSE
ciphercaesar-0.1.1.dist-info/METADATA
ciphercaesar-0.1.1.dist-info/WHEEL
ciphercaesar-0.1.1.dist-info/top_level.txt
ciphercaesar-0.1.1.dist-info/RECORD
