Metadata-Version: 2.1
Name: ciphercaesar
Version: 0.1.1
Summary: A Package to Cipher text
Home-page: https://github.com/ishan090/ciphercaesar
Author: Ishan Kashyap
Author-email: ishan.kashyap@sahyadrischool.org
License: MIT
Keywords: cipher,monoalphabetic,caesar
Platform: UNKNOWN
Classifier: Development Status :: 3 - Alpha
Classifier: Intended Audience :: Developers
Classifier: Topic :: Software Development :: Build Tools
Classifier: License :: OSI Approved :: MIT License
Classifier: Programming Language :: Python :: 3
